llama_index/py.typed
llama_index/vector_stores/vectorx/__init__.py
llama_index/vector_stores/vectorx/base.py
llama_index_vector_stores_vectorx-0.1.0.dist-info/METADATA
llama_index_vector_stores_vectorx-0.1.0.dist-info/WHEEL
llama_index_vector_stores_vectorx-0.1.0.dist-info/licenses/LICENSE
llama_index_vector_stores_vectorx-0.1.0.dist-info/RECORD
