Metadata-Version: 2.4
Name: llama-index-vector-stores-vectorx
Version: 0.1.0
Summary: LlamaIndex VectorX vector store integration
Author-email: Your Name <you@example.com>
License-Expression: MIT
License-File: LICENSE
Requires-Python: <4.0,>=3.10
Requires-Dist: llama-index-core<0.14,>=0.13.0
Requires-Dist: llama-index-embeddings-huggingface
Requires-Dist: vecx>=0.1.0
